fabric_cf/.DS_Store
fabric_cf/__init__.py
fabric_cf/orchestrator/__init__.py
fabric_cf/orchestrator/orchestrator_proxy.py
fabric_cf/orchestrator/swagger_client/__init__.py
fabric_cf/orchestrator/swagger_client/api_client.py
fabric_cf/orchestrator/swagger_client/configuration.py
fabric_cf/orchestrator/swagger_client/rest.py
fabric_cf/orchestrator/swagger_client/api/__init__.py
fabric_cf/orchestrator/swagger_client/api/metrics_api.py
fabric_cf/orchestrator/swagger_client/api/poas_api.py
fabric_cf/orchestrator/swagger_client/api/resources_api.py
fabric_cf/orchestrator/swagger_client/api/slices_api.py
fabric_cf/orchestrator/swagger_client/api/slivers_api.py
fabric_cf/orchestrator/swagger_client/api/version_api.py
fabric_cf/orchestrator/swagger_client/models/__init__.py
fabric_cf/orchestrator/swagger_client/models/metrics.py
fabric_cf/orchestrator/swagger_client/models/poa.py
fabric_cf/orchestrator/swagger_client/models/poa_data.py
fabric_cf/orchestrator/swagger_client/models/poa_post.py
fabric_cf/orchestrator/swagger_client/models/poa_post_data.py
fabric_cf/orchestrator/swagger_client/models/poa_post_data_keys.py
fabric_cf/orchestrator/swagger_client/models/poa_post_data_vcpu_cpu_map.py
fabric_cf/orchestrator/swagger_client/models/resource.py
fabric_cf/orchestrator/swagger_client/models/resources.py
fabric_cf/orchestrator/swagger_client/models/slice.py
fabric_cf/orchestrator/swagger_client/models/slice_details.py
fabric_cf/orchestrator/swagger_client/models/slices.py
fabric_cf/orchestrator/swagger_client/models/slices_post.py
fabric_cf/orchestrator/swagger_client/models/sliver.py
fabric_cf/orchestrator/swagger_client/models/slivers.py
fabric_cf/orchestrator/swagger_client/models/status200_ok_no_content.py
fabric_cf/orchestrator/swagger_client/models/status200_ok_no_content_data.py
fabric_cf/orchestrator/swagger_client/models/status200_ok_paginated.py
fabric_cf/orchestrator/swagger_client/models/status200_ok_single.py
fabric_orchestrator_client-1.9.1.dist-info/licenses/LICENSE
fabric_orchestrator_client-1.9.1.dist-info/WHEEL
fabric_orchestrator_client-1.9.1.dist-info/METADATA
fabric_orchestrator_client-1.9.1.dist-info/RECORD
