Metadata-Version: 2.4
Name: fabric_orchestrator_client
Version: 1.9.1
Summary: Fabric Orchestrator API
Keywords: Swagger,Fabric Orchestrator API
Author-email: Komal Thareja <kthare10@renci.org>
Requires-Python: >=3.9
Classifier: Programming Language :: Python :: 3
Classifier: License :: OSI Approved :: MIT License
Classifier: Operating System :: OS Independent
License-File: LICENSE
Requires-Dist: certifi >= 14.05.14
Requires-Dist: six >= 1.10
Requires-Dist: python_dateutil >= 2.5.3
Requires-Dist: requests>=2.28.1
Requires-Dist: fabric-fim==1.9.1
Requires-Dist: coverage>=4.0.3 ; extra == "test"
Requires-Dist: nose>=1.3.7 ; extra == "test"
Requires-Dist: pluggy>=0.3.1 ; extra == "test"
Requires-Dist: py>=1.4.31 ; extra == "test"
Requires-Dist: randomize>=0.13 ; extra == "test"
Project-URL: Home, https://fabric-testbed.net/
Project-URL: Sources, https://github.com/fabric-testbed/OrchestratorClient
Provides-Extra: test
